llama_index/llms/huggingface/__init__.py
llama_index/llms/huggingface/base.py
llama_index/llms/huggingface/utils.py
llama_index_llms_huggingface-0.6.1.dist-info/METADATA
llama_index_llms_huggingface-0.6.1.dist-info/WHEEL
llama_index_llms_huggingface-0.6.1.dist-info/licenses/LICENSE
llama_index_llms_huggingface-0.6.1.dist-info/RECORD
